poetry_setuptools_scm_plugin/__init__.py
poetry_setuptools_scm_plugin/plugin.py
poetry_setuptools_scm_plugin-0.3.0.dist-info/LICENSE
poetry_setuptools_scm_plugin-0.3.0.dist-info/METADATA
poetry_setuptools_scm_plugin-0.3.0.dist-info/WHEEL
poetry_setuptools_scm_plugin-0.3.0.dist-info/entry_points.txt
poetry_setuptools_scm_plugin-0.3.0.dist-info/RECORD
