Metadata-Version: 2.1
Name: poetry-setuptools-scm-plugin
Version: 0.3.0
Summary: Poetry Plugin that uses setuptools-scm to determine version
Home-page: https://github.com/volkerstampa/poetry-setuptools-scm-plugin
License: Apache-2.0
Keywords: poetry,plugin,version,git
Author: Volker Stampa
Author-email: Volker.Stampa@gmx.net
Maintainer: Volker Stampa
Maintainer-email: Volker.Stampa@gmx.net
Requires-Python: >=3.11,<4.0
Classifier: Development Status :: 4 - Beta
Classifier: Intended Audience :: Developers
Classifier: License :: OSI Approved :: Apache Software License
Classifier: Programming Language :: Python :: 3
Classifier: Programming Language :: Python :: 3.11
Classifier: Programming Language :: Python :: 3.12
Classifier: Programming Language :: Python :: 3.13
Classifier: Programming Language :: Python :: 3 :: Only
Classifier: Topic :: Software Development :: Libraries
Requires-Dist: poetry (>=1.8.2,<3.0.0)
Requires-Dist: setuptools-scm (>=8.0.4,<9.0.0)
